Osmia/__init__.py
Osmia/base_email.py
Osmia/email_attachment.py
Osmia/email_config.py
Osmia/email_message.py
Osmia/file_check.py
Osmia/smtp_service_config.py
osmia-1.3.0.dist-info/licenses/LICENSE
osmia-1.3.0.dist-info/METADATA
osmia-1.3.0.dist-info/WHEEL
osmia-1.3.0.dist-info/top_level.txt
osmia-1.3.0.dist-info/RECORD
