Metadata-Version: 2.4
Name: osmia
Version: 1.3.0
Summary: An ultra-simple and SOLID Python library for sending emails with attachments and HTML or plain text support.
Home-page: https://github.com/Tina-1300/Osmia
Author: Tina
Author-email: tina.xytrfgthuji1348@gmail.com
License: MIT
Classifier: Programming Language :: Python :: 3
Classifier: License :: OSI Approved :: MIT License
Classifier: Operating System :: OS Independent
Classifier: Intended Audience :: Developers
Classifier: Topic :: Communications :: Email
Requires-Python: >=3.13.0
License-File: LICENSE
Dynamic: license-file
